pyziptax/__init__.py
pyziptax/exceptions.py
pyziptax/ziptax.py
pyziptax-1.2.1.dist-info/DESCRIPTION.rst
pyziptax-1.2.1.dist-info/METADATA
pyziptax-1.2.1.dist-info/RECORD
pyziptax-1.2.1.dist-info/WHEEL
pyziptax-1.2.1.dist-info/metadata.json
pyziptax-1.2.1.dist-info/pbr.json
pyziptax-1.2.1.dist-info/top_level.txt
