Metadata-Version: 2.0
Name: pyziptax
Version: 1.2.1
Summary: Python API for accessing sales tax information from Zip-Tax.com
Home-page: http://github.com/albertyw/pyziptax
Author: Albert Wang
Author-email: aywang31@gmail.com
License: Apache
Download-URL: https://github.com/albertyw/pyziptax/archive/v1.2.1.tar.gz
Keywords: tax,ziptax
Platform: UNKNOWN
Classifier: Development Status :: 5 - Production/Stable
Classifier: Environment :: Console
Classifier: Intended Audience :: Developers
Classifier: License :: OSI Approved :: Apache Software License
Classifier: Natural Language :: English
Classifier: Programming Language :: Python
Classifier: Programming Language :: Python :: 2.7
Classifier: Programming Language :: Python :: 3
Classifier: Programming Language :: Python :: 3.4
Classifier: Topic :: Software Development :: Localization
Classifier: Topic :: Office/Business :: Financial :: Accounting
Requires-Dist: requests (>=1.1.0)
